MANIFEST.in
__init__.py
readme.rst
setup.py
tweetup.py
tweetup.egg-info/PKG-INFO
tweetup.egg-info/SOURCES.txt
tweetup.egg-info/dependency_links.txt
tweetup.egg-info/requires.txt
tweetup.egg-info/top_level.txt