Metadata-Version: 1.0
Name: tweetup
Version: 0.1
Summary: Tweetup  module.
Home-page: https://github.com/anurag619/mywork/tree/master/tweet
Author: Anurag Kumar
Author-email: anurag3rdsep@gmail.com
License: MIT
Platform: Linux
